plugincore/__init__.py
plugincore/baseplugin.py
plugincore/configfile.py
plugincore/cors.py
plugincore/logjam.py
plugincore/pluginmanager.py
plugincore/pserv.py
pluginserver-0.8.2.dist-info/licenses/LICENSE.txt
pluginserver-0.8.2.dist-info/METADATA
pluginserver-0.8.2.dist-info/WHEEL
pluginserver-0.8.2.dist-info/entry_points.txt
pluginserver-0.8.2.dist-info/top_level.txt
pluginserver-0.8.2.dist-info/RECORD
